[{"id": 1, "updated_time": "22:26:06", "data": [{"id": 1, "election_area": "Kathmandu-1", "candidates": [{"id": 1, "name": "Prakashman Singh", "party": "Nepali Congress", "vote": 7143, "area": 1}, {"id": 2, "name": "Rabindra Mishra", "party": "Rastriya Prajatantra Party", "vote": 7018, "area": 1}, {"id": 3, "name": "Pukar Bam", "party": "Rastriya Swatantra Party", "vote": 4115, "area": 1}]}, {"id": 2, "election_area": "Kathmandu-2", "candidates": [{"id": 4, "name": "Sobita Gautam", "party": "Rastriya Swatantra Party", "vote": 15229, "area": 2}, {"id": 5, "name": "Maniram Phuyal", "party": "CPN UML", "vote": 11555, "area": 2}, {"id": 6, "name": "Kanti Devi Pokharel", "party": "Rastriya Prajatantra Party", "vote": 11014, "area": 2}]}, {"id": 3, "election_area": "Kathmandu-3", "candidates": [{"id": 7, "name": "Santosh Chalise", "party": "Nepali Congress", "vote": 15158, "area": 3}, {"id": 8, "name": "Krishna Bahadur Rai", "party": "CPN UML", "vote": 11196, "area": 3}, {"id": 9, "name": "Durga Bikram Thapa Chettri", "party": "Rastriya Swatantra Party", "vote": 5865, "area": 3}]}, {"id": 4, "election_area": "Kathmandu-4", "candidates": [{"id": 10, "name": "Gagan Kumar Thapa", "party": "Nepali Congress", "vote": 21302, "area": 4}, {"id": 11, "name": "Rajan Bhattarai", "party": "CPN UML", "vote": 13855, "area": 4}, {"id": 12, "name": "Dr. Thakur Mohan Shrestha", "party": "Rastriya Prajatantra Party", "vote": 4050, "area": 4}]}, {"id": 5, "election_area": "Kathmandu-5", "candidates": [{"id": 13, "name": "Pradip Poudel", "party": "Nepali Congress", "vote": 15237, "area": 5}, {"id": 14, "name": "Ishwor Pokhrel", "party": "CPN UML", "vote": 10175, "area": 5}, {"id": 15, "name": "Dr.Pranaya Shemser Rana", "party": "Rastriya Swatantra Party", "vote": 5473, "area": 5}]}, {"id": 6, "election_area": "Kathmandu-6", "candidates": [{"id": 16, "name": "Shishir Khanal", "party": "Rastriya Swatantra Party", "vote": 14204, "area": 6}, {"id": 17, "name": "Shabendra Khanal", "party": "CPN UML", "vote": 8911, "area": 6}, {"id": 18, "name": "Bhemsen Das Pradhan", "party": "Nepali Congress", "vote": 8805, "area": 6}]}, {"id": 7, "election_area": "Kathmandu-7", "candidates": [{"id": 19, "name": "Ganesh Parajuli", "party": "Rastriya Swatantra Party", "vote": 8743, "area": 7}, {"id": 20, "name": "Shyam Kumar Ghimire", "party": "CPN UML", "vote": 6800, "area": 7}, {"id": 21, "name": "Ashmita Singh (Manusi) Yami Bhattarai", "party": "CPN Maoist", "vote": 6063, "area": 7}]}, {"id": 8, "election_area": "Kathmandu-8", "candidates": [{"id": 23, "name": "Suman Sayami", "party": "Hamro Nepali Party", "vote": 5889, "area": 8}, {"id": 24, "name": "Jeewan Ram Shrestha", "party": "CPN (Unified Socialist)", "vote": 4877, "area": 8}, {"id": 22, "name": "Biraj Bhakta Shrestha", "party": "Rastriya Swatantra Party", "vote": 10105, "area": 8}]}, {"id": 9, "election_area": "Kathmandu-9", "candidates": [{"id": 25, "name": "Krishna Gopal Shrestha", "party": "CPN UML", "vote": 11956, "area": 9}, {"id": 26, "name": "Tek Bahadur Pokheral", "party": "Rastriya Swatantra Party", "vote": 10961, "area": 9}, {"id": 27, "name": "Kalpana Dhamal", "party": "CPN Maoist", "vote": 6402, "area": 9}]}, {"id": 10, "election_area": "Kathmandu-10", "candidates": [{"id": 29, "name": "Himesh K.c", "party": "CPN UML", "vote": 11786, "area": 10}, {"id": 28, "name": "Rajendra Kumar K.C", "party": "Nepali Congress", "vote": 14448, "area": 10}, {"id": 30, "name": "Pradip Bista", "party": "Rastriya Swatantra Party", "vote": 7347, "area": 10}]}, {"id": 11, "election_area": "Kathmandu-1 (1)", "candidates": [{"id": 31, "name": "Dipendra Shrestha", "party": "Nepali Congress", "vote": 6300, "area": 11}, {"id": 32, "name": "Nabin Shahi", "party": "Rastriya Prajatantra Party", "vote": 3504, "area": 11}, {"id": 33, "name": "Ram Prasad Amgain", "party": "CPN UML", "vote": 2297, "area": 11}]}, {"id": 12, "election_area": "Kathmandu-1 (2)", "candidates": [{"id": 34, "name": "Suraj Chandra Lamichhane", "party": "Nepali Congress", "vote": 4510, "area": 12}, {"id": 35, "name": "Ganesh Prasad Dulal", "party": "CPN UML", "vote": 2753, "area": 12}, {"id": 36, "name": "Yagya Bahadur Shah", "party": "Rastriya Prajatantra Party", "vote": 1855, "area": 12}]}, {"id": 13, "election_area": "Kathmandu-2 (1)", "candidates": [{"id": 37, "name": "Sunil K.C", "party": "Rastriya Prajatantra Party", "vote": 6598, "area": 13}, {"id": 38, "name": "Sanu Kumar Shrestha", "party": "CPN UML", "vote": 5079, "area": 13}, {"id": 39, "name": "Dhurba K.C", "party": "Nepali Congress", "vote": 3847, "area": 13}]}, {"id": 14, "election_area": "Kathmandu-2 (2)", "candidates": [{"id": 40, "name": "Raju Bist", "party": "Rastriya Prajatantra Party", "vote": 12163, "area": 14}, {"id": 41, "name": "Suvarna Shrestha", "party": "CPN UML", "vote": 9090, "area": 14}, {"id": 42, "name": "Bharat Prasad Phuyal", "party": "CPN (Unified Socialist)", "vote": 8015, "area": 14}]}, {"id": 15, "election_area": "Kathmandu-3 (1)", "candidates": [{"id": 43, "name": "Chiring Dorje Lama", "party": "Nepali Congress", "vote": 4558, "area": 15}, {"id": 44, "name": "Chandraman Lama", "party": "CPN UML", "vote": 3415, "area": 15}, {"id": 45, "name": "Dipendra Lama", "party": "Independent", "vote": 2933, "area": 15}]}, {"id": 16, "election_area": "Kathmandu-3 (2)", "candidates": [{"id": 46, "name": "Bimal Thakuri", "party": "Nepali Congress", "vote": 10617, "area": 16}, {"id": 47, "name": "Rameshwor Phuyal", "party": "CPN UML", "vote": 8247, "area": 16}, {"id": 48, "name": "Kamal Sunar", "party": "Rastriya Prajatantra Party", "vote": 2617, "area": 16}]}, {"id": 17, "election_area": "Kathmandu-4 (1)", "candidates": [{"id": 50, "name": "Riddhi Pratap Jung Bahadur Rana", "party": "Rastriya Prajatantra Party", "vote": 6604, "area": 17}, {"id": 51, "name": "Tej Prasad Dhakal", "party": "CPN UML", "vote": 4335, "area": 17}, {"id": 49, "name": "Shreeram Lamichhane", "party": "Nepali Congress", "vote": 7125, "area": 17}]}, {"id": 18, "election_area": "Kathmandu-4 (2)", "candidates": [{"id": 52, "name": "Jayram Thapa", "party": "CPN UML", "vote": 10417, "area": 18}, {"id": 53, "name": "Kusum Kumar Karki", "party": "CPN (Unified Socialist)", "vote": 8283, "area": 18}, {"id": 54, "name": "Punya Lal Shrestha", "party": "Rastriya Prajatantra Party", "vote": 5177, "area": 18}]}, {"id": 19, "election_area": "Kathmandu-5 (1)", "candidates": [{"id": 55, "name": "Rajendra Prajapati", "party": "Rastriya Prajatantra Party", "vote": 4304, "area": 19}, {"id": 56, "name": "Bhairab Sapkota", "party": "Nepali Congress", "vote": 3887, "area": 19}, {"id": 57, "name": "Narayan Bahadur Silwal", "party": "CPN UML", "vote": 3494, "area": 19}]}, {"id": 20, "election_area": "Kathmandu-5 (2)", "candidates": [{"id": 58, "name": "Shyam Bahadur Khadka", "party": "Nepali Congress", "vote": 9742, "area": 20}, {"id": 59, "name": "Dipak Niraula", "party": "CPN UML", "vote": 8414, "area": 20}, {"id": 60, "name": "Susan Lal Shrestha", "party": "Rastriya Prajatantra Party", "vote": 5636, "area": 20}]}, {"id": 21, "election_area": "Kathmandu-6 (1)", "candidates": [{"id": 61, "name": "Hariprabha Khadgi", "party": "Nepali Congress", "vote": 4656, "area": 21}, {"id": 62, "name": "Niresh Lal Singh Maharjan", "party": "CPN UML", "vote": 3936, "area": 21}, {"id": 63, "name": "Jagat Sagar Maharjan", "party": "Rastriya Prajatantra Party", "vote": 3798, "area": 21}]}, {"id": 22, "election_area": "Kathmandu-6 (2)", "candidates": [{"id": 64, "name": "Aman Kumar Maskey", "party": "CPN UML", "vote": 8059, "area": 22}, {"id": 65, "name": "Bishnubhakta Timalsina", "party": "Nepali Congress", "vote": 6671, "area": 22}, {"id": 66, "name": "Chirag Man Sinha Kunwar", "party": "Rastriya Prajatantra Party", "vote": 3576, "area": 22}]}, {"id": 23, "election_area": "Kathmandu-7 (1)", "candidates": [{"id": 67, "name": "Basant Prasad Manandhar", "party": "CPN (Unified Socialist)", "vote": 5866, "area": 23}, {"id": 68, "name": "Jiwan Manandhar", "party": "CPN UML", "vote": 4555, "area": 23}, {"id": 69, "name": "Rojina Gurung", "party": "Rastriya Prajatantra Party", "vote": 4280, "area": 23}]}, {"id": 24, "election_area": "Kathmandu-7 (2)", "candidates": [{"id": 70, "name": "Prakash Shrestha", "party": "CPN UML", "vote": 5218, "area": 24}, {"id": 71, "name": "Sabin Tamang", "party": "Nepali Congress", "vote": 5137, "area": 24}, {"id": 72, "name": "Lal Kumar Lama", "party": "Rastriya Prajatantra Party", "vote": 2797, "area": 24}]}, {"id": 25, "election_area": "Kathmandu-8 (1)", "candidates": [{"id": 73, "name": "Shailendra Man Bajracharya", "party": "Hamro Nepali Party", "vote": 5470, "area": 25}, {"id": 74, "name": "Rajesh Shakya", "party": "CPN UML", "vote": 3718, "area": 25}, {"id": 75, "name": "Raju Raj Joshi", "party": "Nepali Congress", "vote": 3673, "area": 25}]}, {"id": 26, "election_area": "Kathmandu-8 (2)", "candidates": [{"id": 76, "name": "Uddhav Thapa", "party": "Rastriya Prajatantra Party", "vote": 3349, "area": 26}, {"id": 77, "name": "Nima Ghyamche Tamang", "party": "CPN UML", "vote": 1916, "area": 26}, {"id": 78, "name": "Amin Pandeya", "party": "Nepali Congress", "vote": 1839, "area": 26}]}, {"id": 27, "election_area": "Kathmandu-9 (1)", "candidates": [{"id": 79, "name": "Nuraj Bajracharya", "party": "Rastriya Prajatantra Party", "vote": 4653, "area": 27}, {"id": 80, "name": "Hari Krishna Dangol", "party": "CPN UML", "vote": 4552, "area": 27}, {"id": 81, "name": "Nanu Maiya Bastola", "party": "Nepali Congress", "vote": 4020, "area": 27}]}, {"id": 28, "election_area": "Kathmandu-9 (2)", "candidates": [{"id": 82, "name": "Keshav Prasad Pokharel", "party": "CPN UML", "vote": 8459, "area": 28}, {"id": 83, "name": "Shyam Krishna Khadka", "party": "Nepali Congress", "vote": 7341, "area": 28}, {"id": 84, "name": "Dil Kumar Karki", "party": "Rastriya Prajatantra Party", "vote": 4775, "area": 28}]}, {"id": 29, "election_area": "Kathmandu-10 (1)", "candidates": [{"id": 85, "name": "Pukar Maharjan", "party": "Nepali Congress", "vote": 10082, "area": 29}, {"id": 86, "name": "Umesh Raj Sapkota", "party": "Rastriya Prajatantra Party", "vote": 7400, "area": 29}, {"id": 87, "name": "Shiva Bhakti Balami", "party": "CPN UML", "vote": 7309, "area": 29}]}, {"id": 30, "election_area": "Kathmandu-10 (2)", "candidates": [{"id": 88, "name": "Ram Ale Magar", "party": "CPN (Unified Socialist)", "vote": 5818, "area": 30}, {"id": 89, "name": "Ramsharan Alemagar", "party": "CPN UML", "vote": 5188, "area": 30}, {"id": 90, "name": "Surya Bahadur Maharjan", "party": "Rastriya Prajatantra Party", "vote": 3110, "area": 30}]}, {"id": 31, "election_area": "Dadeldhura-1", "candidates": [{"id": 91, "name": "Sher Bahadur Deuba", "party": "Nepali Congress", "vote": 25534, "area": 31}, {"id": 92, "name": "Sagar Dhakal", "party": "Independent", "vote": 13042, "area": 31}, {"id": 93, "name": "Karna Bahadur Malla", "party": "Nepali Congress (BP)", "vote": 7535, "area": 31}]}, {"id": 32, "election_area": "Chitwan-2", "candidates": [{"id": 94, "name": "Rabi Lamichhane", "party": "Rastriya Swatantra Party", "vote": 49264, "area": 32}, {"id": 95, "name": "Umesh Shrestha", "party": "Nepali Congress", "vote": 14983, "area": 32}, {"id": 96, "name": "Krishna Bhakta Pokhrel", "party": "CPN UML", "vote": 14647, "area": 32}]}, {"id": 33, "election_area": "Lalitpur-3", "candidates": [{"id": 97, "name": "Toshima Karki", "party": "Rastriya Swatantra Party", "vote": 31136, "area": 33}, {"id": 98, "name": "Amrit Khadka", "party": "CPN UML", "vote": 12963, "area": 33}, {"id": 99, "name": "Pampha Bhushal", "party": "CPN Maoist", "vote": 8769, "area": 33}]}, {"id": 34, "election_area": "Jhapa-3", "candidates": [{"id": 100, "name": "Rajendra Prasad Lingden", "party": "Rastriya Prajatantra Party", "vote": 40662, "area": 34}, {"id": 101, "name": "Krishna Prasad Sitaula", "party": "Nepali Congress", "vote": 37386, "area": 34}, {"id": 102, "name": "Prakash Pathak", "party": "Rastriya Swatantra Party", "vote": 3461, "area": 34}]}, {"id": 35, "election_area": "Jhapa-1", "candidates": [{"id": 103, "name": "Biswa Prakash Sharma", "party": "Nepali Congress", "vote": 39624, "area": 35}, {"id": 104, "name": "Agni Prasad Kharel", "party": "CPN UML", "vote": 25349, "area": 35}, {"id": 105, "name": "Om Nath Bhandari", "party": "Rastriya Swatantra Party", "vote": 8564, "area": 35}]}, {"id": 36, "election_area": "Jhapa-5", "candidates": [{"id": 106, "name": "KP Sharma Oli", "party": "CPN UML", "vote": 52319, "area": 36}, {"id": 107, "name": "Khagendra Adhikari", "party": "Nepali Congress", "vote": 23743, "area": 36}, {"id": 108, "name": "Suresh Kumar Poheral", "party": "Rastriya Swatantra Party", "vote": 11759, "area": 36}]}, {"id": 37, "election_area": "Gorkha-2", "candidates": [{"id": 109, "name": "Puspa Kamal Dahal (Prachanda)", "party": "CPN Maoist", "vote": 26109, "area": 37}, {"id": 110, "name": "Kabindra Burlakoti", "party": "Rastriya Swatantra Party", "vote": 12639, "area": 37}, {"id": 111, "name": "Abdus Salam Miya", "party": "CPN UML", "vote": 7395, "area": 37}]}, {"id": 38, "election_area": "Rauthat-1", "candidates": [{"id": 113, "name": "Ajay Kumar Gupta", "party": "CPN UML", "vote": 26922, "area": 38}, {"id": 114, "name": "Rajendra Prasad Shah", "party": "Janamat Party", "vote": 1206, "area": 38}, {"id": 112, "name": "Madhav Kumar Nepal", "party": "CPN (Unified Socialist)", "vote": 33522, "area": 38}]}, {"id": 39, "election_area": "Illam-1", "candidates": [{"id": 115, "name": "Mahesh Basnet", "party": "CPN UML", "vote": 25753, "area": 39}, {"id": 116, "name": "Jhalanath Khanal", "party": "CPN (Unified Socialist)", "vote": 23089, "area": 39}, {"id": 117, "name": "Buddha Lal Meche", "party": "Mangol National Organization", "vote": 2442, "area": 39}]}, {"id": 40, "election_area": "Morang-6", "candidates": [{"id": 118, "name": "Dr. Shekhar Koirala", "party": "Nepali Congress", "vote": 35224, "area": 40}, {"id": 119, "name": "Lal Babu Pandit", "party": "CPN UML", "vote": 22946, "area": 40}, {"id": 120, "name": "Yadav Kumar Pradhan", "party": "Rastriya Swatantra Party", "vote": 9140, "area": 40}]}, {"id": 41, "election_area": "Rupandehi-2", "candidates": [{"id": 121, "name": "Bishnu Prasad Paudel", "party": "CPN UML", "vote": 27148, "area": 41}, {"id": 122, "name": "Ganesh Paudel", "party": "Rastriya Swatantra Party", "vote": 25782, "area": 41}, {"id": 123, "name": "Keshav Bahadur Thapa Magar", "party": "Rastriya Janamukti Party", "vote": 22010, "area": 41}]}]}]